AUTHORS
CHANGELOG
INSTALL
LICENSE
MANIFEST.in
README.md
REQUIREMENTS.txt
setup.py
bin/opyum
docs/Makefile
docs/source/conf.py
docs/source/index.rst
docs/source/quickstart.rst
docs/source/rst_guide.rst
opyum/__init__.py
opyum/compile.py
opyum/decompile.py
opyum/hook.py
opyum/transform.py
opyum/utils.py
opyum.egg-info/PKG-INFO
opyum.egg-info/SOURCES.txt
opyum.egg-info/dependency_links.txt
opyum.egg-info/not-zip-safe
opyum.egg-info/requires.txt
opyum.egg-info/top_level.txt
opyum/optimizations/__init__.py
opyum/optimizations/builtin_constant_propagation.py
opyum/optimizations/constant_folding.py
opyum/optimizations/custom_constant_propagation.py
opyum/optimizations/dead_code_elimination.py
opyum/optimizations/format_positions.py
opyum/optimizations/globals_to_locals.py
opyum/optimizations/mult_to_sum.py
opyum/optimizations/pow_to_mult.py
opyum/optimizations/yield_to_yield_from.py
tests/runtests.py
tests/tests.py